otter/__init__.py
otter/core.py
otter/py.typed
otter/config/__init__.py
otter/config/cli.py
otter/config/env.py
otter/config/model.py
otter/config/yaml.py
otter/manifest/__init__.py
otter/manifest/manifest_manager.py
otter/manifest/model.py
otter/scratchpad/__init__.py
otter/scratchpad/model.py
otter/step/__init__.py
otter/step/model.py
otter/step/step_reporter.py
otter/storage/__init__.py
otter/storage/google.py
otter/storage/model.py
otter/storage/noop.py
otter/task/__init__.py
otter/task/model.py
otter/task/task_registry.py
otter/task/task_reporter.py
otter/tasks/__init__.py
otter/tasks/copy.py
otter/tasks/download.py
otter/tasks/explode.py
otter/tasks/explode_glob.py
otter/tasks/find_latest.py
otter/tasks/hello_world.py
otter/util/__init__.py
otter/util/download.py
otter/util/errors.py
otter/util/fs.py
otter/util/logger.py
otter/validators/__init__.py
otter/validators/file.py
opentargets_otter-25.0.16.dist-info/METADATA
opentargets_otter-25.0.16.dist-info/WHEEL
opentargets_otter-25.0.16.dist-info/entry_points.txt
opentargets_otter-25.0.16.dist-info/licenses/LICENSE
opentargets_otter-25.0.16.dist-info/RECORD
