Metadata-Version: 2.4
Name: opentargets-otter
Version: 25.0.16
Summary: Open Targets Task ExcutoR
Author-email: Open Targets Core Team <devs@opentargets.org>
License: Apache-2.0
License-File: LICENSE
Requires-Python: >=3.11
Requires-Dist: filelock==3.18.0
Requires-Dist: google-cloud-storage==3.1.1
Requires-Dist: loguru==0.7.3
Requires-Dist: pydantic==2.11.7
Requires-Dist: pyyaml==6.0.2
Requires-Dist: requests==2.32.4
Requires-Dist: urllib3==2.5.0
Provides-Extra: docs
Requires-Dist: autodoc-pydantic>=2.2.0; extra == 'docs'
Requires-Dist: esbonio>=0.16.5; extra == 'docs'
Requires-Dist: sphinx-autobuild>=2024.10.3; extra == 'docs'
Requires-Dist: sphinx-issues>=5.0.1; extra == 'docs'
Requires-Dist: sphinx-rtd-theme>=3.0.2; extra == 'docs'
Requires-Dist: sphinx>=8.2.3; extra == 'docs'
Provides-Extra: test
Requires-Dist: coverage==7.9.1; extra == 'test'
Requires-Dist: freezegun==1.5.2; extra == 'test'
Requires-Dist: pytest-mock==3.14.1; extra == 'test'
Requires-Dist: pytest==8.4.1; extra == 'test'
